pytest_ibutsu/__init__.py
pytest_ibutsu/archiver.py
pytest_ibutsu/modeling.py
pytest_ibutsu/newhooks.py
pytest_ibutsu/py.typed
pytest_ibutsu/pytest_plugin.py
pytest_ibutsu/s3_uploader.py
pytest_ibutsu/sender.py
pytest_ibutsu-3.1.4.dist-info/METADATA
pytest_ibutsu-3.1.4.dist-info/WHEEL
pytest_ibutsu-3.1.4.dist-info/entry_points.txt
pytest_ibutsu-3.1.4.dist-info/licenses/LICENSE
pytest_ibutsu-3.1.4.dist-info/RECORD
