Metadata-Version: 2.4
Name: pytest-ibutsu
Version: 3.1.4
Summary: A plugin to sent pytest results to an Ibutsu server
Project-URL: Source, https://github.com/ibutsu/pytest-ibutsu
Project-URL: Tracker, https://github.com/ibutsu/pytest-ibutsu/issues
Maintainer: Raoul Snyman, Dmitry Misharov, Mike Shriver
License-Expression: MIT
License-File: LICENSE
Classifier: Development Status :: 4 - Beta
Classifier: Framework :: Pytest
Classifier: Intended Audience :: Developers
Classifier: License :: OSI Approved :: MIT License
Classifier: Operating System :: OS Independent
Classifier: Programming Language :: Python
Classifier: Programming Language :: Python :: 3.11
Classifier: Programming Language :: Python :: 3.12
Classifier: Programming Language :: Python :: 3.13
Classifier: Programming Language :: Python :: Implementation :: CPython
Classifier: Programming Language :: Python :: Implementation :: PyPy
Classifier: Topic :: Software Development :: Testing
Requires-Python: >=3.11
Requires-Dist: attrs
Requires-Dist: boto3
Requires-Dist: cattrs
Requires-Dist: ibutsu-client>=3.1.1
Requires-Dist: pytest
